[{"id":1,"first_name":"Jeanie","last_name":"Slowan","email":"jslowan0@about.me","gender":"Female"},
{"id":2,"first_name":"Nolie","last_name":"Antusch","email":"nantusch1@tmall.com","gender":"Female"},
{"id":3,"first_name":"Lelia","last_name":"Buckthought","email":"lbuckthought2@howstuffworks.com","gender":"Bigender"},
{"id":4,"first_name":"Valentijn","last_name":"O'Connel","email":"voconnel3@umich.edu","gender":null},
{"id":5,"first_name":"Quinn","last_name":"Lenchenko","email":"qlenchenko4@wp.com","gender":"Female"},
{"id":6,"first_name":"Melany","last_name":"MacGiffin","email":"mmacgiffin5@nationalgeographic.com","gender":"Genderfluid"},
{"id":7,"first_name":"Vachel","last_name":"Duley","email":"vduley6@tinyurl.com","gender":"Male"},
{"id":8,"first_name":"Cornell","last_name":"Lovick","email":"clovick7@slideshare.net","gender":"Male"},
{"id":9,"first_name":"Rodney","last_name":"McCracken","email":"rmccracken8@skype.com","gender":"Genderqueer"},
{"id":10,"first_name":"Adrienne","last_name":"Sturley","email":"asturley9@chicagotribune.com","gender":"Female"},
{"id":11,"first_name":"Niccolo","last_name":"Sickling","email":"nsicklinga@vistaprint.com","gender":"Male"},
{"id":12,"first_name":"Tim","last_name":"Farren","email":"tfarrenb@deviantart.com","gender":"Male"},
{"id":13,"first_name":"Caesar","last_name":"Freemantle","email":"cfreemantlec@mashable.com","gender":"Male"},
{"id":14,"first_name":"Emmott","last_name":"Penelli","email":"epenellid@google.fr","gender":"Male"},
{"id":15,"first_name":"Kelsy","last_name":"Garfitt","email":"kgarfitte@springer.com","gender":"Female"},
{"id":16,"first_name":"Blake","last_name":"Jordanson","email":"bjordansonf@tamu.edu","gender":null},
{"id":17,"first_name":"Mahalia","last_name":"Mowsley","email":"mmowsleyg@amazon.co.jp","gender":"Female"},
{"id":18,"first_name":"Putnam","last_name":"Agg","email":"paggh@baidu.com","gender":"Male"},
{"id":19,"first_name":"Lida","last_name":"Ferrarotti","email":"lferrarottii@taobao.com","gender":"Female"},
{"id":20,"first_name":"Bran","last_name":"Jarrell","email":"bjarrellj@google.de","gender":"Male"},
{"id":21,"first_name":"Miner","last_name":"Belshaw","email":"mbelshawk@nba.com","gender":"Polygender"},
{"id":22,"first_name":"Isobel","last_name":"Muldrew","email":"imuldrewl@github.com","gender":"Female"},
{"id":23,"first_name":"Shermie","last_name":"Elden","email":"seldenm@google.ru","gender":"Male"},
{"id":24,"first_name":"Natty","last_name":"Saul","email":"nsauln@merriam-webster.com","gender":"Male"},
{"id":25,"first_name":"Hoebart","last_name":"Madeley","email":"hmadeleyo@flickr.com","gender":"Male"},
{"id":26,"first_name":"Genevra","last_name":"Jahndel","email":"gjahndelp@stanford.edu","gender":"Female"},
{"id":27,"first_name":"Nalani","last_name":"Cocozza","email":"ncocozzaq@people.com.cn","gender":"Female"},
{"id":28,"first_name":"Karyn","last_name":"Weekes","email":"kweekesr@twitpic.com","gender":"Female"},
{"id":29,"first_name":"Perrine","last_name":"Jurewicz","email":"pjurewiczs@bravesites.com","gender":"Female"},
{"id":30,"first_name":"Deana","last_name":"Houselee","email":"dhouseleet@theglobeandmail.com","gender":"Female"},
{"id":31,"first_name":"Susanna","last_name":"Drees","email":"sdreesu@goo.ne.jp","gender":"Female"},
{"id":32,"first_name":"Pate","last_name":"Golland","email":"pgollandv@yahoo.com","gender":"Male"},
{"id":33,"first_name":"Ludovico","last_name":"Grayer","email":"lgrayerw@i2i.jp","gender":"Male"},
{"id":34,"first_name":"Daren","last_name":"Jedraszek","email":"djedraszekx@zimbio.com","gender":"Male"},
{"id":35,"first_name":"Salomo","last_name":"Clandillon","email":"sclandillony@foxnews.com","gender":"Male"},
{"id":36,"first_name":"Bonita","last_name":"Fowlie","email":"bfowliez@admin.ch","gender":"Female"},
{"id":37,"first_name":"Janenna","last_name":"Relf","email":"jrelf10@photobucket.com","gender":"Female"},
{"id":38,"first_name":"Corbet","last_name":"Postlethwaite","email":"cpostlethwaite11@sbwire.com","gender":"Male"},
{"id":39,"first_name":"Cyrill","last_name":"Sandry","email":"csandry12@biglobe.ne.jp","gender":"Male"},
{"id":40,"first_name":"Anstice","last_name":"Lelliott","email":"alelliott13@china.com.cn","gender":"Female"},
{"id":41,"first_name":"Barr","last_name":"Bendin","email":"bbendin14@nps.gov","gender":"Male"},
{"id":42,"first_name":"Tiffy","last_name":"Tow","email":"ttow15@vkontakte.ru","gender":"Female"},
{"id":43,"first_name":"Sergei","last_name":"Ravenhill","email":"sravenhill16@census.gov","gender":"Male"},
{"id":44,"first_name":"Law","last_name":"Aughtie","email":"laughtie17@youku.com","gender":"Male"},
{"id":45,"first_name":"Alfie","last_name":"Lambert","email":"alambert18@buzzfeed.com","gender":"Male"},
{"id":46,"first_name":"Katrina","last_name":"Olivari","email":"kolivari19@reddit.com","gender":"Genderfluid"},
{"id":47,"first_name":"Latisha","last_name":"MacGiany","email":"lmacgiany1a@huffingtonpost.com","gender":"Female"},
{"id":48,"first_name":"Lew","last_name":"Finey","email":"lfiney1b@sina.com.cn","gender":"Male"},
{"id":49,"first_name":"Glenine","last_name":"Burdekin","email":"gburdekin1c@histats.com","gender":"Female"},
{"id":50,"first_name":"Oralle","last_name":"Carah","email":"ocarah1d@cornell.edu","gender":"Female"},
{"id":51,"first_name":"Dido","last_name":"Leech","email":"dleech1e@last.fm","gender":"Bigender"},
{"id":52,"first_name":"Chrisse","last_name":"Theuff","email":"ctheuff1f@mtv.com","gender":"Male"},
{"id":53,"first_name":"Alysa","last_name":"Littleover","email":"alittleover1g@acquirethisname.com","gender":"Female"},
{"id":54,"first_name":"Van","last_name":"Braid","email":"vbraid1h@nbcnews.com","gender":"Male"},
{"id":55,"first_name":"Joey","last_name":"Clemente","email":"jclemente1i@paginegialle.it","gender":"Male"},
{"id":56,"first_name":"Alyosha","last_name":"Donovin","email":"adonovin1j@businessweek.com","gender":"Male"},
{"id":57,"first_name":"Rosalia","last_name":"Divver","email":"rdivver1k@clickbank.net","gender":"Female"},
{"id":58,"first_name":"Orelee","last_name":"Gilbey","email":"ogilbey1l@nytimes.com","gender":"Female"},
{"id":59,"first_name":"Lauren","last_name":"Drew","email":"ldrew1m@amazon.co.uk","gender":"Female"},
{"id":60,"first_name":"Camel","last_name":"Bondley","email":"cbondley1n@jalbum.net","gender":"Female"},
{"id":61,"first_name":"Felicdad","last_name":"Denniss","email":"fdenniss1o@ifeng.com","gender":"Female"},
{"id":62,"first_name":"Nisse","last_name":"Mohun","email":"nmohun1p@imdb.com","gender":"Female"},
{"id":63,"first_name":"Warde","last_name":"Galego","email":"wgalego1q@princeton.edu","gender":"Male"},
{"id":64,"first_name":"Gerik","last_name":"Habbema","email":"ghabbema1r@vinaora.com","gender":"Male"},
{"id":65,"first_name":"Alexina","last_name":"Corcut","email":"acorcut1s@cafepress.com","gender":"Genderfluid"},
{"id":66,"first_name":"Jock","last_name":"Corballis","email":"jcorballis1t@phoca.cz","gender":"Male"},
{"id":67,"first_name":"Cletus","last_name":"Craigmile","email":"ccraigmile1u@simplemachines.org","gender":"Male"},
{"id":68,"first_name":"Nicolea","last_name":"Itzak","email":"nitzak1v@qq.com","gender":"Female"},
{"id":69,"first_name":"Sula","last_name":"Norwich","email":"snorwich1w@house.gov","gender":"Female"},
{"id":70,"first_name":"Griffy","last_name":"Waddam","email":"gwaddam1x@accuweather.com","gender":"Male"},
{"id":71,"first_name":"Katleen","last_name":"Knowling","email":"kknowling1y@eventbrite.com","gender":"Female"},
{"id":72,"first_name":"Ashbey","last_name":"Chavez","email":"achavez1z@pbs.org","gender":"Male"},
{"id":73,"first_name":"Mikaela","last_name":"Greatbach","email":"mgreatbach20@sina.com.cn","gender":"Female"},
{"id":74,"first_name":"Bobina","last_name":"Goddard","email":"bgoddard21@technorati.com","gender":"Female"},
{"id":75,"first_name":"Kevon","last_name":"Layburn","email":"klayburn22@chronoengine.com","gender":"Male"},
{"id":76,"first_name":"Nahum","last_name":"Curds","email":"ncurds23@de.vu","gender":null},
{"id":77,"first_name":"Gavan","last_name":"Tommaseo","email":"gtommaseo24@rediff.com","gender":"Male"},
{"id":78,"first_name":"Urban","last_name":"Rubenczyk","email":"urubenczyk25@prlog.org","gender":"Polygender"},
{"id":79,"first_name":"Bert","last_name":"Stanfield","email":"bstanfield26@ezinearticles.com","gender":"Genderfluid"},
{"id":80,"first_name":"Taffy","last_name":"Nalder","email":"tnalder27@washingtonpost.com","gender":"Female"},
{"id":81,"first_name":"Ame","last_name":"Wennington","email":"awennington28@sciencedirect.com","gender":"Female"},
{"id":82,"first_name":"Tripp","last_name":"Battie","email":"tbattie29@princeton.edu","gender":"Male"},
{"id":83,"first_name":"Wilbur","last_name":"Maria","email":"wmaria2a@dagondesign.com","gender":"Male"},
{"id":84,"first_name":"Shannah","last_name":"Unwins","email":"sunwins2b@facebook.com","gender":"Female"},
{"id":85,"first_name":"Rosie","last_name":"Baskeyfield","email":"rbaskeyfield2c@sitemeter.com","gender":"Female"},
{"id":86,"first_name":"Audrey","last_name":"Betser","email":"abetser2d@mit.edu","gender":"Female"},
{"id":87,"first_name":"Elsworth","last_name":"Noto","email":"enoto2e@ibm.com","gender":"Male"},
{"id":88,"first_name":"Finn","last_name":"Neno","email":"fneno2f@salon.com","gender":"Male"},
{"id":89,"first_name":"Agnella","last_name":"Bidewel","email":"abidewel2g@usa.gov","gender":"Female"},
{"id":90,"first_name":"Anselma","last_name":"Attock","email":"aattock2h@toplist.cz","gender":"Female"},
{"id":91,"first_name":"Yetta","last_name":"Tacker","email":"ytacker2i@wikimedia.org","gender":null},
{"id":92,"first_name":"Waiter","last_name":"Retallick","email":"wretallick2j@japanpost.jp","gender":"Male"},
{"id":93,"first_name":"Dani","last_name":"Burlingham","email":"dburlingham2k@desdev.cn","gender":"Male"},
{"id":94,"first_name":"Leonanie","last_name":"Pybworth","email":"lpybworth2l@reuters.com","gender":"Female"},
{"id":95,"first_name":"Boycey","last_name":"Wikey","email":"bwikey2m@accuweather.com","gender":"Male"},
{"id":96,"first_name":"Darla","last_name":"Gavigan","email":"dgavigan2n@acquirethisname.com","gender":"Genderqueer"},
{"id":97,"first_name":"Iago","last_name":"Gullivan","email":"igullivan2o@miitbeian.gov.cn","gender":"Male"},
{"id":98,"first_name":"Dean","last_name":"Burnip","email":"dburnip2p@auda.org.au","gender":"Male"},
{"id":99,"first_name":"Alyda","last_name":"Priest","email":"apriest2q@blogspot.com","gender":"Female"},
{"id":100,"first_name":"Alika","last_name":"Grinnikov","email":"agrinnikov2r@mac.com","gender":"Female"}]